apoli_bolt/__init__.py
apoli_bolt/py.typed
apoli_bolt-0.0.9.dist-info/METADATA
apoli_bolt-0.0.9.dist-info/WHEEL
apoli_bolt-0.0.9.dist-info/RECORD
