Metadata-Version: 2.1
Name: apoli_bolt
Version: 0.0.9
Summary: Bolt datapack apoli integration.
License: MIT
Keywords: beet,mecha,bolt,python,minecraft,datapack,minecraft-commands,mcfunction,apoli_integration,library,apoli,event,event-handler
Author: ThatRobin
Author-email: thatrobin3001@gmail.com
Requires-Python: >=3.11,<4.0
Classifier: License :: OSI Approved :: MIT License
Classifier: Programming Language :: Python :: 3
Classifier: Programming Language :: Python :: 3.11
Classifier: Programming Language :: Python :: 3.12
Requires-Dist: beet (>=0.84.0)
Requires-Dist: bolt (>=0.31.0)
Requires-Dist: mecha (>=0.67.0)
